ukbb_pan_ancestry/__init__.py
ukbb_pan_ancestry/resources/__init__.py
ukbb_pan_ancestry/resources/generic.py
ukbb_pan_ancestry/resources/genotypes.py
ukbb_pan_ancestry/resources/ld.py
ukbb_pan_ancestry/resources/phenotypes.py
ukbb_pan_ancestry/resources/results.py
ukbb_pan_ancestry/utils/__init__.py
ukbb_pan_ancestry/utils/phenotype_loading.py
ukbb_pan_ancestry/utils/results.py
ukbb_pan_ancestry/utils/results_loading.py
ukbb_pan_ancestry-0.0.2.dist-info/LICENSE
ukbb_pan_ancestry-0.0.2.dist-info/METADATA
ukbb_pan_ancestry-0.0.2.dist-info/WHEEL
ukbb_pan_ancestry-0.0.2.dist-info/top_level.txt
ukbb_pan_ancestry-0.0.2.dist-info/RECORD
